beSMArt/__init__.py
beSMArt/main.py
beSMArt/version.py
beSMArt-1.0.1.dist-info/METADATA
beSMArt-1.0.1.dist-info/WHEEL
beSMArt-1.0.1.dist-info/top_level.txt
beSMArt-1.0.1.dist-info/RECORD
