Metadata-Version: 2.1
Name: beSMArt
Version: 1.0.1
Summary: Connect to SMA solar panel
Home-page: UNKNOWN
Author: Patryk Niedzwiedzinski
Author-email: pniedzwiedzinski19@gmail.com
License: MIT
Platform: UNKNOWN
Requires-Dist: requests
